[{"id":"text:en-components/users/SwitchUserModal-0","value":{"title":"Switch Member","description1":"An an Administrator, you can switch to another member by entering their Username or User ID.","description2":"When you're done, you can <strong>Switch to Another Member</strong> or back to yourself."},"localOverride":false,"__typename":"CachedAsset"},{"id":"text:en-components/users/SwitchUserForm-0","value":{"SwitchUserForm.userAttrOptions.login.label":"Username","SwitchUserForm.userAttrOptions.id.label":"User ID","SwitchUserForm.userAttrOptions.id.info":"You can search by either a User ID or the member's profile URL","SwitchUserForm.userLogin.placeholder":"","SwitchUserForm.userLogin.validate.error":"Enter an Username","SwitchUserForm.userId.validate.error":"Enter an User ID","SwitchUserForm.userId.notValidUser.error":"Enter a valid User ID","UserFetching.noResults.title":"No results found","UserFetching.noResults.message":"Try a different search term","switchMember":"Switch Member","cancel":"Cancel","successTitle":"Member Switched","successMessage":"You are viewing the community as {userLogin}","error.mutation.title":"Error","error.mutation.description":"An unidentified problem occurred during the action you took. Please try again later.","error.user.login.switch_to_yourself":"You cannot switch to yourself","error.user.user.doesnt_exist":"Member does not exist","error.user.login.switch_no_permission":"You do not have permission to switch to this member"},"localOverride":false,"__typename":"CachedAsset"},{"id":"text:en-shared/client/components/form/InputEditForm-0","value":{"reCaptcha.error.title":"Unexpected Error","reCaptcha.error.message":"Please try refreshing the page and submitting again."},"localOverride":false,"__typename":"CachedAsset"},{"id":"text:en-shared/client/components/authentication/ReCaptchaPrivacyTos-0","value":{"privacytos":"This site is protected by reCAPTCHA and the Google <privacyLink>Privacy Policy</privacyLink> and <tosLink>Terms of Service</tosLink> apply."},"localOverride":false,"__typename":"CachedAsset"},{"id":"text:en-shared/client/components/common/Loading/LoadingDot-0","value":{"title":"Loading..."},"localOverride":false,"__typename":"CachedAsset"},{"id":"text:en-shared/client/components/common/Loading/LoadingLinear-0","value":{"title":"Loading..."},"localOverride":false,"__typename":"CachedAsset"},{"id":"text:en-shared/client/components/common/InfoPopover-0","value":{"moreInformation":"More Information"},"localOverride":false,"__typename":"CachedAsset"},{"id":"text:en-shared/client/components/form/UnsavedChangedDialog-0","value":{"unsavedChangesWarningDialog.title":"Unsaved Changes","unsavedChangesWarningDialog.body":"Do you want to go back and save the changes?","unsavedChangesWarningDialog.submit":"Discard Changes","unsavedChangesWarningDialog.cancel":"Go Back"},"localOverride":false,"__typename":"CachedAsset"},{"id":"text:en-shared/client/components/common/ConfirmationDialog-0","value":{"submit":"OK","cancel":"Cancel","useCheckboxConfirmError":"Select the checkbox to confirm action"},"localOverride":false,"__typename":"CachedAsset"},{"id":"text:en-shared/client/components/common/QueryHandler-0","value":{"title":"Query Handler"},"localOverride":false,"__typename":"CachedAsset"},{"id":"text:en-shared/client/components/common/ApolloErrorAlert-0","value":{"title":"GraphQL Errors:"},"localOverride":false,"__typename":"CachedAsset"},{"id":"text:en-shared/client/components/users/UserAvatar-0","value":{"altText":"{login}'s avatar","altTextGeneric":"User's avatar"},"localOverride":false,"__typename":"CachedAsset"},{"id":"text:en-shared/client/components/users/UserLogin-0","value":{"title":"{login}"},"localOverride":false,"__typename":"CachedAsset"}]